OutlineMapper/__init__.py
OutlineMapper/process_image.py
OutlineMapper-0.1.3.dist-info/LICENSE.txt
OutlineMapper-0.1.3.dist-info/METADATA
OutlineMapper-0.1.3.dist-info/WHEEL
OutlineMapper-0.1.3.dist-info/top_level.txt
OutlineMapper-0.1.3.dist-info/RECORD
