Metadata-Version: 2.1
Name: OutlineMapper
Version: 0.1.3
Summary: Simple outline mapper for images, using color clustering
Home-page: https://github.com/RyuKaSa/OutlineMapper
Author: Ryukasa
Author-email: william.bogdanovic@yahoo.fr
License-File: LICENSE.txt
Requires-Dist: numpy
Requires-Dist: pillow
Requires-Dist: matplotlib
Requires-Dist: scikit-learn
Requires-Dist: scipy
